djangoldp_edc/__init__.py
djangoldp_edc/apps.py
djangoldp_edc/exceptions.py
djangoldp_edc/middleware.py
djangoldp_edc/utils.py
djangoldp_edc/permissions/__init__.py
djangoldp_edc/permissions/base.py
djangoldp_edc/permissions/v3.py
djangoldp_edc/permissions/v3_auto.py
djangoldp_edc/permissions/v3_discovery.py
djangoldp_edc/permissions/v3_fallback.py
djangoldp_edc/tests/__init__.py
djangoldp_edc/tests/runner.py
djangoldp_edc/tests/test_base.py
djangoldp_edc/tests/test_middleware.py
djangoldp_edc/tests/test_permissions.py
djangoldp_edc/tests/test_permissions_v3.py
djangoldp_edc/tests/test_utils.py
djangoldp_edc-1.0.1.dist-info/METADATA
djangoldp_edc-1.0.1.dist-info/WHEEL
djangoldp_edc-1.0.1.dist-info/top_level.txt
djangoldp_edc-1.0.1.dist-info/RECORD
