Metadata-Version: 2.4
Name: djangoldp_edc
Version: 1.0.1
Summary: DjangoLDP package for Eclipse Dataspace Connector (EDC) integration and permissions
Home-page: https://git.startinblox.com/djangoldp-packages/djangoldp-edc
Author: Startin'blox
Author-email: tech@startinblox.com
License: MIT
Requires-Dist: djangoldp>=4.0.0
Requires-Dist: requests>=2.25.0
Provides-Extra: dev
Requires-Dist: factory_boy>=2.11.0; extra == "dev"
